htmpy/__init__.py
htmpy/css.py
htmpy/cssautomations.py
htmpy/html.py
htmpy/htmlautomations.py
htmpy-0.3.3.dist-info/LICENSE
htmpy-0.3.3.dist-info/METADATA
htmpy-0.3.3.dist-info/WHEEL
htmpy-0.3.3.dist-info/top_level.txt
htmpy-0.3.3.dist-info/RECORD
