Metadata-Version: 2.1
Name: htmpy
Version: 0.3.3
Summary: Package to create automatically webpages
Home-page: https://github.com/riioze/htmpy
Author: riioze
Author-email: riioze0@gmail.com
License: UNKNOWN
Platform: UNKNOWN
Classifier: Programming Language :: Python :: 3
Classifier: License :: OSI Approved :: MIT License
Classifier: Operating System :: OS Independent
Requires-Python: >=3.6
